LessJianmingJiaochengWaiBowang/README.md
LessJianmingJiaochengWaiBowang/__init__.py
LessJianmingJiaochengWaiBowang/__main__.py
LessJianmingJiaochengWaiBowang/file.epub
LessJianmingJiaochengWaiBowang/index.html
LessJianmingJiaochengWaiBowang/css/__init__.py
LessJianmingJiaochengWaiBowang/css/annotations.css
LessJianmingJiaochengWaiBowang/css/main.css
LessJianmingJiaochengWaiBowang/css/normalize.css
LessJianmingJiaochengWaiBowang/css/popup.css
LessJianmingJiaochengWaiBowang/font/__init__.py
LessJianmingJiaochengWaiBowang/font/fontello.eot
LessJianmingJiaochengWaiBowang/font/fontello.svg
LessJianmingJiaochengWaiBowang/font/fontello.ttf
LessJianmingJiaochengWaiBowang/font/fontello.woff
LessJianmingJiaochengWaiBowang/img/__init__.py
LessJianmingJiaochengWaiBowang/img/annotator-glyph-sprite.png
LessJianmingJiaochengWaiBowang/img/annotator-icon-sprite.png
LessJianmingJiaochengWaiBowang/img/apple-touch-icon.png
LessJianmingJiaochengWaiBowang/img/cancelfullscreen.png
LessJianmingJiaochengWaiBowang/img/close.png
LessJianmingJiaochengWaiBowang/img/fullscreen.png
LessJianmingJiaochengWaiBowang/img/loader.gif
LessJianmingJiaochengWaiBowang/img/menu-icon.png
LessJianmingJiaochengWaiBowang/img/save.png
LessJianmingJiaochengWaiBowang/img/saved.png
LessJianmingJiaochengWaiBowang/img/settings-s.png
LessJianmingJiaochengWaiBowang/img/settings.png
LessJianmingJiaochengWaiBowang/img/star.png
LessJianmingJiaochengWaiBowang/js/__init__.py
LessJianmingJiaochengWaiBowang/js/epub.js
LessJianmingJiaochengWaiBowang/js/epub.min.js
LessJianmingJiaochengWaiBowang/js/epub.min.map
LessJianmingJiaochengWaiBowang/js/hooks.min.js
LessJianmingJiaochengWaiBowang/js/hooks.min.map
LessJianmingJiaochengWaiBowang/js/reader.js
LessJianmingJiaochengWaiBowang/js/reader.js.map
LessJianmingJiaochengWaiBowang/js/reader.min.js
LessJianmingJiaochengWaiBowang/js/reader.min.map
LessJianmingJiaochengWaiBowang/js/hooks/__init__.py
LessJianmingJiaochengWaiBowang/js/hooks/extensions/__init__.py
less_jianming_jiaocheng_wai_bowang-2024.3.3.0.dist-info/METADATA
less_jianming_jiaocheng_wai_bowang-2024.3.3.0.dist-info/WHEEL
less_jianming_jiaocheng_wai_bowang-2024.3.3.0.dist-info/entry_points.txt
less_jianming_jiaocheng_wai_bowang-2024.3.3.0.dist-info/top_level.txt
less_jianming_jiaocheng_wai_bowang-2024.3.3.0.dist-info/RECORD
